{"commitInfo":{"timestamp":1717127532036,"operation":"CREATE TABLE","operationParameters":{"isManaged":"false","description":null,"partitionBy":"[\"month\"]","properties":"{}"},"isolationLevel":"Serializable","isBlindAppend":true,"operationMetrics":{},"engineInfo":"Apache-Spark/3.5.1 Delta-Lake/3.1.0","txnId":"be2ef858-4d1e-453c-911c-f36d734c89a1"}}
{"metaData":{"id":"a82d4f1d-6728-468f-8822-379600fb1d5f","format":{"provider":"parquet","options":{}},"schemaString":"{\"type\":\"struct\",\"fields\":[{\"name\":\"window\",\"type\":{\"type\":\"struct\",\"fields\":[{\"name\":\"start\",\"type\":\"timestamp\",\"nullable\":true,\"metadata\":{}},{\"name\":\"end\",\"type\":\"timestamp\",\"nullable\":true,\"metadata\":{}}]},\"nullable\":false,\"metadata\":{}},{\"name\":\"n\",\"type\":\"long\",\"nullable\":false,\"metadata\":{}},{\"name\":\"month\",\"type\":\"date\",\"nullable\":false,\"metadata\":{}}]}","partitionColumns":["month"],"configuration":{},"createdTime":1717127531973}}
{"protocol":{"minReaderVersion":1,"minWriterVersion":2}}
